{
  "active": true,
  "code": "20941",
  "name": {
    "ru_RU": "Расчеты по доходам от штрафных санкций за нарушение условий контрактов (договоров)"
  },
  "foreign": false,
  "numerical": false,
  "amounttype": "None",
  "journalnumber": "5",
  "kosgudb": "564",
  "kosgukr": "664",
  "budgetclassificationtype": "None",
  "offbalance": false,
  "type": "Active",
  "analyticsList": [],
  "propertyValues": {},
  "grants": {},
  "meta": {
    "mnemo": "20941",
    "title": {
      "ru_RU": "20941"
    },
    "description": {}
  }
}