{
  "periodictype": "ForAllDocumentsThatType",
  "autonumerizer": true,
  "numeratortype": "Number",
  "length": 5,
  "uniquecontrol": true,
  "acceptaccountingprocessing": true,
  "automovedeletion": true,
  "autorownumerizer": true,
  "accounting": false,
  "calculation": false,
  "operationalaccounting": false,
  "createoperation": "Always",
  "headerrequsites": [
    {
      "meta": {
        "mnemo": "tap.RashodnyeKassovyeOrdera.hr.Oplacheno",
        "title": {
          "ru_RU": "Оплачено",
          "en_EN": "Oplacheno"
        },
        "description": {}
      },
      "type": {
        "mnemo": "primitive.boolean"
      },
      "properties": {},
      "required": false
    },
    {
      "meta": {
        "mnemo": "tap.RashodnyeKassovyeOrdera.hr.Annulirovano",
        "title": {
          "ru_RU": "Аннулировано",
          "en_EN": "Annulirovano"
        },
        "description": {}
      },
      "type": {
        "mnemo": "primitive.boolean"
      },
      "properties": {},
      "required": false
    },
    {
      "meta": {
        "mnemo": "tap.RashodnyeKassovyeOrdera.hr.Podrazdelenie",
        "title": {
          "ru_RU": "Подразделение",
          "en_EN": "Podrazdelenie"
        },
        "description": {}
      },
      "type": {
        "mnemo": "tap.Podrazdeleniya"
      },
      "properties": {},
      "required": false
    },
    {
      "meta": {
        "mnemo": "tap.RashodnyeKassovyeOrdera.hr.Podrazdeleniekor",
        "title": {
          "ru_RU": "Подразделение (кор.)",
          "en_EN": "Podrazdelenie kor"
        },
        "description": {}
      },
      "type": {
        "mnemo": "tap.Podrazdeleniya"
      },
      "properties": {},
      "required": false
    },
    {
      "meta": {
        "mnemo": "tap.RashodnyeKassovyeOrdera.hr.KorSchet",
        "title": {
          "ru_RU": "Кор. счет",
          "en_EN": "Kor schet"
        },
        "description": {}
      },
      "type": {
        "mnemo": "primitive.account"
      },
      "properties": {
        "showanalytic": "false"
      },
      "required": true
    },
    {
      "meta": {
        "mnemo": "tap.RashodnyeKassovyeOrdera.hr.KodAnalitichUcheta",
        "title": {
          "ru_RU": "Код аналитич. учета",
          "en_EN": "Kod analitich ucheta"
        },
        "description": {}
      },
      "type": {
        "mnemo": "primitive.text"
      },
      "properties": {
        "unlimited": "false",
        "length": "10"
      },
      "required": false
    },
    {
      "meta": {
        "mnemo": "tap.RashodnyeKassovyeOrdera.hr.SchetKt",
        "title": {
          "ru_RU": "Счет Кт",
          "en_EN": "Schet Kt"
        },
        "description": {}
      },
      "type": {
        "mnemo": "primitive.account"
      },
      "properties": {
        "showanalytic": "false"
      },
      "required": true
    },
    {
      "meta": {
        "mnemo": "tap.RashodnyeKassovyeOrdera.hr.Summa",
        "title": {
          "ru_RU": "Сумма(всего)",
          "en_EN": "Summa"
        },
        "description": {}
      },
      "type": {
        "mnemo": "primitive.real"
      },
      "properties": {
        "precision": "2",
        "length": "15",
        "unsigned": "true"
      },
      "required": true
    },
    {
      "meta": {
        "mnemo": "tap.RashodnyeKassovyeOrdera.hr.CelevoeNaznachenie",
        "title": {
          "ru_RU": "Целевое назначение",
          "en_EN": "Celevoe naznachenie"
        },
        "description": {}
      },
      "type": {
        "mnemo": "tap.CelevyeNaznacheniyaKassovyhOrderov"
      },
      "properties": {},
      "required": false
    },
    {
      "meta": {
        "mnemo": "tap.RashodnyeKassovyeOrdera.hr.Kontragent",
        "title": {
          "ru_RU": "Контрагент",
          "en_EN": "Kontragent"
        },
        "description": {}
      },
      "type": {
        "mnemo": "tap.Kontragenty"
      },
      "properties": {},
      "required": false
    },
    {
      "meta": {
        "mnemo": "tap.RashodnyeKassovyeOrdera.hr.FIO",
        "title": {
          "ru_RU": "ФИО",
          "en_EN": "FIO"
        },
        "description": {}
      },
      "type": {
        "mnemo": "primitive.text"
      },
      "properties": {
        "unlimited": "true",
        "length": "14"
      },
      "required": false
    },
    {
      "meta": {
        "mnemo": "tap.RashodnyeKassovyeOrdera.hr.PoDokumentu",
        "title": {
          "ru_RU": "По документу",
          "en_EN": "Po dokumentu"
        },
        "description": {}
      },
      "type": {
        "mnemo": "primitive.text"
      },
      "properties": {
        "unlimited": "true",
        "length": "14"
      },
      "required": false
    },
    {
      "meta": {
        "mnemo": "tap.RashodnyeKassovyeOrdera.hr.Dogovor",
        "title": {
          "ru_RU": "Договор",
          "en_EN": "Dogovor"
        },
        "description": {}
      },
      "type": {
        "mnemo": "tap.DogovoryIObyazatelstva"
      },
      "properties": {},
      "required": false
    },
    {
      "meta": {
        "mnemo": "tap.RashodnyeKassovyeOrdera.hr.Osnovanie",
        "title": {
          "ru_RU": "Основание",
          "en_EN": "Osnovanie"
        },
        "description": {}
      },
      "type": {
        "mnemo": "tap.OsnovaniyaKassovyhOrderov"
      },
      "properties": {},
      "required": false
    },
    {
      "meta": {
        "mnemo": "tap.RashodnyeKassovyeOrdera.hr.Prilozhenie",
        "title": {
          "ru_RU": "Приложение",
          "en_EN": "Prilozhenie"
        },
        "description": {}
      },
      "type": {
        "mnemo": "primitive.text"
      },
      "properties": {
        "unlimited": "true",
        "length": "14"
      },
      "required": false
    },
    {
      "meta": {
        "mnemo": "tap.RashodnyeKassovyeOrdera.tr.FormirovatProvodkiPoIspolneniiuPlanaDohodov",
        "title": {
          "ru_RU": "Формировать проводки по исполнению плана доходов",
          "en_EN": "Formirovat provodki po ispolneniiu plana dohodov"
        },
        "description": {}
      },
      "type": {
        "mnemo": "primitive.boolean"
      },
      "properties": {},
      "required": false
    },
    {
      "meta": {
        "mnemo": "tap.RashodnyeKassovyeOrdera.hr.RazdelLicevyhSchetov",
        "title": {
          "ru_RU": "Раздел лицевых счетов",
          "en_EN": "Razdel licevyh schetov"
        },
        "description": {}
      },
      "type": {
        "mnemo": "tap.RazdelyLicevyhSchetov"
      },
      "properties": {},
      "required": false
    },
    {
      "meta": {
        "mnemo": "tap.RashodnyeKassovyeOrdera.hr.Rukovoditel",
        "title": {
          "ru_RU": "Руководитель",
          "en_EN": "Rukovoditel"
        },
        "description": {}
      },
      "type": {
        "mnemo": "tap.Sotrudniki"
      },
      "properties": {},
      "required": false
    },
    {
      "meta": {
        "mnemo": "tap.RashodnyeKassovyeOrdera.hr.GlBuhgalter",
        "title": {
          "ru_RU": "Гл. бухгалтер",
          "en_EN": "Gl buhgalter"
        },
        "description": {}
      },
      "type": {
        "mnemo": "tap.Sotrudniki"
      },
      "properties": {},
      "required": false
    },
    {
      "meta": {
        "mnemo": "tap.RashodnyeKassovyeOrdera.hr.Kassir",
        "title": {
          "ru_RU": "Кассир",
          "en_EN": "Kassir"
        },
        "description": {}
      },
      "type": {
        "mnemo": "tap.Sotrudniki"
      },
      "properties": {},
      "required": false
    },
    {
      "meta": {
        "mnemo": "tap.RashodnyeKassovyeOrdera.hr.Kommentariii",
        "title": {
          "ru_RU": "Комментарий",
          "en_EN": "Kommentariii"
        },
        "description": {}
      },
      "type": {
        "mnemo": "primitive.text"
      },
      "properties": {
        "unlimited": "true",
        "length": "14"
      },
      "required": false
    }
  ],
  "tablerequsites": [
    {
      "istotal": true,
      "meta": {
        "mnemo": "tap.RashodnyeKassovyeOrdera.tr.Summa",
        "title": {
          "ru_RU": "Сумма",
          "en_EN": "Summa"
        },
        "description": {}
      },
      "type": {
        "mnemo": "primitive.real"
      },
      "properties": {
        "precision": "2",
        "length": "15",
        "unsigned": "true"
      },
      "required": true
    },
    {
      "meta": {
        "mnemo": "tap.RashodnyeKassovyeOrdera.tr.KFO",
        "title": {
          "ru_RU": "КФО",
          "en_EN": "KFO"
        },
        "description": {}
      },
      "type": {
        "mnemo": "tap.KFO"
      },
      "properties": {},
      "required": true
    },
    {
      "meta": {
        "mnemo": "tap.RashodnyeKassovyeOrdera.tr.KPS",
        "title": {
          "ru_RU": "КПС",
          "en_EN": "KPS"
        },
        "description": {}
      },
      "type": {
        "mnemo": "tap.KPS"
      },
      "properties": {},
      "required": true
    },
    {
      "meta": {
        "mnemo": "tap.RashodnyeKassovyeOrdera.tr.KEK",
        "title": {
          "ru_RU": "КЭК",
          "en_EN": "KEK"
        },
        "description": {}
      },
      "type": {
        "mnemo": "tap.KK"
      },
      "properties": {},
      "required": true
    },
    {
      "meta": {
        "mnemo": "tap.RashodnyeKassovyeOrdera.tr.SchetRaschetov",
        "title": {
          "ru_RU": "Счет расчетов",
          "en_EN": "Schet raschetov"
        },
        "description": {}
      },
      "type": {
        "mnemo": "primitive.account"
      },
      "properties": {
        "showanalytic": "true"
      },
      "required": false
    },
    {
      "meta": {
        "mnemo": "tap.RashodnyeKassovyeOrdera.tr.VidRaschetov",
        "title": {
          "ru_RU": "Вид расчетов",
          "en_EN": "Vid raschetov"
        },
        "description": {}
      },
      "type": {
        "mnemo": "tap.VidyRaschetovPoZaiimam"
      },
      "properties": {},
      "required": false
    }
  ],
  "basedondocuments": {
    "isthebasis": [],
    "maybethebasisforanykind": false
  },
  "formdescription": {
    "script": {
      "title": "script",
      "sources": ""
    }
  },
  "formdocument": {
    "script": {
      "title": "script",
      "sources": ""
    }
  },
  "script": {
    "title": "Скрипт документа Расходные кассовые ордера",
    "sources": ""
  },
  "algorithms": [
    {
      "mnemo": "tap.RashodnyeKassovyeOrdera.VydachaNalichnyhKontragentu"
    },
    {
      "mnemo": "tap.RashodnyeKassovyeOrdera.VnesenieNalichnyhDsNaBankovskiiiSchet"
    },
    {
      "mnemo": "tap.RashodnyeKassovyeOrdera.VnesenieNalichnyhNaLicevoiiSchet"
    },
    {
      "mnemo": "tap.RashodnyeKassovyeOrdera.VydachaDeponentskoiiZadolzhennosti"
    },
    {
      "mnemo": "tap.RashodnyeKassovyeOrdera.VydachaNalichnyhVoVremennomRasporyazheniiStoronnimKontragentam"
    },
    {
      "mnemo": "tap.RashodnyeKassovyeOrdera.VydachaNalichnyhPodOtchet"
    },
    {
      "mnemo": "tap.RashodnyeKassovyeOrdera.PogashenieZadolzhennostiPoDolgovymObyazatelstvam"
    },
    {
      "mnemo": "tap.RashodnyeKassovyeOrdera.PredostavlenieKreditovZaiimovssud"
    },
    {
      "mnemo": "tap.RashodnyeKassovyeOrdera.SpisanieSummVyyavlennyhNedostachPoterDs"
    }
  ],
  "printedformset": [],
  "grants": {},
  "meta": {
    "mnemo": "tap.RashodnyeKassovyeOrdera",
    "title": {
      "ru_RU": "Расходные кассовые ордера",
      "en_EN": "Rashodnye kassovye ordera"
    },
    "description": {}
  }
}