{
  "periodictype": "ForAllDocumentsThatType",
  "autonumerizer": true,
  "numeratortype": "Text",
  "length": 24,
  "uniquecontrol": true,
  "acceptaccountingprocessing": true,
  "automovedeletion": true,
  "autorownumerizer": true,
  "accounting": false,
  "calculation": false,
  "operationalaccounting": false,
  "createoperation": "Always",
  "headerrequsites": [
    {
      "meta": {
        "mnemo": "TestLis.PrihodnyeKassovyeOrdera.hr.Summa",
        "title": {
          "ru_RU": "Сумма",
          "en_EN": "Summa"
        },
        "description": {}
      },
      "type": {
        "mnemo": "primitive.real"
      },
      "properties": {
        "precision": "2",
        "length": "14",
        "unsigned": "false"
      },
      "required": false
    },
    {
      "meta": {
        "mnemo": "TestLis.PrihodnyeKassovyeOrdera.hr.Kassir",
        "title": {
          "ru_RU": "Кассир",
          "en_EN": "Kassir"
        },
        "description": {}
      },
      "type": {
        "mnemo": "Razrabotka.Sotrudniki"
      },
      "properties": {},
      "required": false
    },
    {
      "meta": {
        "mnemo": "TestLis.PrihodnyeKassovyeOrdera.hr.Operaciya",
        "title": {
          "ru_RU": "Операция",
          "en_EN": "Operaciya"
        },
        "description": {}
      },
      "type": {
        "mnemo": "Razrabotka.Operacii"
      },
      "properties": {},
      "required": false
    },
    {
      "meta": {
        "mnemo": "TestLis.PrihodnyeKassovyeOrdera.hr.Organizaciya",
        "title": {
          "ru_RU": "Организация",
          "en_EN": "Organizaciya"
        },
        "description": {}
      },
      "type": {
        "mnemo": "Razrabotka.Kontragenty"
      },
      "properties": {},
      "required": false
    },
    {
      "meta": {
        "mnemo": "TestLis.PrihodnyeKassovyeOrdera.hr.Sotrudnik",
        "title": {
          "ru_RU": "Сотрудник",
          "en_EN": "Sotrudnik"
        },
        "description": {}
      },
      "type": {
        "mnemo": "Razrabotka.Sotrudniki"
      },
      "properties": {},
      "required": false
    },
    {
      "meta": {
        "mnemo": "TestLis.PrihodnyeKassovyeOrdera.hr.Podrazdelenie",
        "title": {
          "ru_RU": "Подразделение",
          "en_EN": "Podrazdelenie"
        },
        "description": {}
      },
      "type": {
        "mnemo": "Razrabotka.Podrazdeleniya"
      },
      "properties": {},
      "required": false
    },
    {
      "meta": {
        "mnemo": "TestLis.PrihodnyeKassovyeOrdera.hr.PrinyatoOt",
        "title": {
          "ru_RU": "Принято от",
          "en_EN": "Prinyato ot"
        },
        "description": {}
      },
      "type": {
        "mnemo": "primitive.text"
      },
      "properties": {
        "unlimited": "false",
        "length": "300"
      },
      "required": false
    },
    {
      "meta": {
        "mnemo": "TestLis.PrihodnyeKassovyeOrdera.hr.Osnovanie",
        "title": {
          "ru_RU": "Основание",
          "en_EN": "Osnovanie"
        },
        "description": {}
      },
      "type": {
        "mnemo": "Razrabotka.OsnovaniyaPoKassovymOrderam"
      },
      "properties": {},
      "required": false
    },
    {
      "meta": {
        "mnemo": "TestLis.PrihodnyeKassovyeOrdera.hr.Prilozhenie",
        "title": {
          "ru_RU": "Приложение",
          "en_EN": "Prilozhenie"
        },
        "description": {}
      },
      "type": {
        "mnemo": "primitive.text"
      },
      "properties": {
        "unlimited": "false",
        "length": "300"
      },
      "required": false
    },
    {
      "meta": {
        "mnemo": "TestLis.PrihodnyeKassovyeOrdera.hr.KPSKRB",
        "title": {
          "ru_RU": "КПС КРБ",
          "en_EN": "KPS KRB"
        },
        "description": {}
      },
      "type": {
        "mnemo": "Razrabotka.KPS"
      },
      "properties": {},
      "required": false
    },
    {
      "meta": {
        "mnemo": "TestLis.PrihodnyeKassovyeOrdera.hr.KPSKDB",
        "title": {
          "ru_RU": "КПС КДБ",
          "en_EN": "KPS KDB"
        },
        "description": {}
      },
      "type": {
        "mnemo": "Razrabotka.KPS"
      },
      "properties": {},
      "required": false
    },
    {
      "meta": {
        "mnemo": "TestLis.PrihodnyeKassovyeOrdera.hr.KPSDlyaScheta334",
        "title": {
          "ru_RU": "КПС для счета 30304",
          "en_EN": "KPS dlya scheta 334"
        },
        "description": {}
      },
      "type": {
        "mnemo": "Razrabotka.KPS"
      },
      "properties": {},
      "required": false
    }
  ],
  "tablerequsites": [
    {
      "meta": {
        "mnemo": "TestLis.PrihodnyeKassovyeOrdera.tr.Operaciya",
        "title": {
          "ru_RU": "Операция",
          "en_EN": "Operaciya"
        },
        "description": {}
      },
      "type": {
        "mnemo": "Razrabotka.Operacii"
      },
      "properties": {},
      "required": false
    },
    {
      "meta": {
        "mnemo": "TestLis.PrihodnyeKassovyeOrdera.tr.TMC",
        "title": {
          "ru_RU": "ТМЦ",
          "en_EN": "TMC"
        },
        "description": {}
      },
      "type": {
        "mnemo": "Razrabotka.MaterialnyeZapasy"
      },
      "properties": {},
      "required": false
    },
    {
      "meta": {
        "mnemo": "TestLis.PrihodnyeKassovyeOrdera.tr.KVFO",
        "title": {
          "ru_RU": "КВФО",
          "en_EN": "KVFO"
        },
        "description": {}
      },
      "type": {
        "mnemo": "Razrabotka.KFO"
      },
      "properties": {},
      "required": false
    },
    {
      "meta": {
        "mnemo": "TestLis.PrihodnyeKassovyeOrdera.tr.KPSDb",
        "title": {
          "ru_RU": "КПС дб",
          "en_EN": "KPS db"
        },
        "description": {}
      },
      "type": {
        "mnemo": "Razrabotka.KPS"
      },
      "properties": {},
      "required": false
    },
    {
      "meta": {
        "mnemo": "TestLis.PrihodnyeKassovyeOrdera.tr.Debet",
        "title": {
          "ru_RU": "Дебет",
          "en_EN": "Debet"
        },
        "description": {}
      },
      "type": {
        "mnemo": "primitive.account"
      },
      "properties": {
        "showanalytic": "true"
      },
      "required": false
    },
    {
      "meta": {
        "mnemo": "TestLis.PrihodnyeKassovyeOrdera.tr.KOSGUDb",
        "title": {
          "ru_RU": "КОСГУ дб",
          "en_EN": "KOSGU db"
        },
        "description": {}
      },
      "type": {
        "mnemo": "Razrabotka.KOSGUEKR"
      },
      "properties": {},
      "required": false
    },
    {
      "meta": {
        "mnemo": "TestLis.PrihodnyeKassovyeOrdera.tr.KPSKr",
        "title": {
          "ru_RU": "КПС кр",
          "en_EN": "KPS kr"
        },
        "description": {}
      },
      "type": {
        "mnemo": "Razrabotka.KPS"
      },
      "properties": {},
      "required": false
    },
    {
      "meta": {
        "mnemo": "TestLis.PrihodnyeKassovyeOrdera.tr.Kredit",
        "title": {
          "ru_RU": "Кредит",
          "en_EN": "Kredit"
        },
        "description": {}
      },
      "type": {
        "mnemo": "primitive.account"
      },
      "properties": {
        "showanalytic": "true"
      },
      "required": false
    },
    {
      "meta": {
        "mnemo": "TestLis.PrihodnyeKassovyeOrdera.tr.KOSGUKr",
        "title": {
          "ru_RU": "КОСГУ кр",
          "en_EN": "KOSGU kr"
        },
        "description": {}
      },
      "type": {
        "mnemo": "Razrabotka.KOSGUEKR"
      },
      "properties": {},
      "required": false
    },
    {
      "meta": {
        "mnemo": "TestLis.PrihodnyeKassovyeOrdera.tr.RasshifrovkaOperacii",
        "title": {
          "ru_RU": "Расшифровка операции",
          "en_EN": "Rasshifrovka operacii"
        },
        "description": {}
      },
      "type": {
        "mnemo": "Razrabotka.RasshifrovkiOperaciii"
      },
      "properties": {},
      "required": false
    },
    {
      "istotal": false,
      "meta": {
        "mnemo": "TestLis.PrihodnyeKassovyeOrdera.tr.SummaBezNDS",
        "title": {
          "ru_RU": "Сумма без НДС",
          "en_EN": "Summa bez NDS"
        },
        "description": {}
      },
      "type": {
        "mnemo": "primitive.real"
      },
      "properties": {
        "precision": "2",
        "length": "14",
        "unsigned": "false"
      },
      "required": false
    },
    {
      "meta": {
        "mnemo": "TestLis.PrihodnyeKassovyeOrdera.tr.NDS",
        "title": {
          "ru_RU": "НДС%",
          "en_EN": "NDS"
        },
        "description": {}
      },
      "type": {
        "mnemo": "Razrabotka.StavkiNDS"
      },
      "properties": {},
      "required": false
    },
    {
      "istotal": false,
      "meta": {
        "mnemo": "TestLis.PrihodnyeKassovyeOrdera.tr.SummaNDS",
        "title": {
          "ru_RU": "Сумма НДС",
          "en_EN": "Summa NDS"
        },
        "description": {}
      },
      "type": {
        "mnemo": "primitive.real"
      },
      "properties": {
        "precision": "2",
        "length": "14",
        "unsigned": "false"
      },
      "required": false
    },
    {
      "istotal": false,
      "meta": {
        "mnemo": "TestLis.PrihodnyeKassovyeOrdera.tr.VsegoSNDS",
        "title": {
          "ru_RU": "Всего с НДС",
          "en_EN": "Vsego s NDS"
        },
        "description": {}
      },
      "type": {
        "mnemo": "primitive.real"
      },
      "properties": {
        "precision": "2",
        "length": "14",
        "unsigned": "false"
      },
      "required": false
    }
  ],
  "basedondocuments": {
    "isthebasis": [],
    "maybethebasisforanykind": false
  },
  "formdescription": {
    "script": {
      "title": "script",
      "sources": ""
    }
  },
  "formdocument": {
    "script": {
      "title": "script",
      "sources": ""
    }
  },
  "script": {
    "title": "Скрипт документа Приходные кассовые ордера",
    "sources": ""
  },
  "algorithms": [
    {
      "mnemo": "TestLis.PrihodnyeKassovyeOrdera.UchetPrihodnogoKassovogoOrdera__"
    }
  ],
  "printedformset": [],
  "grants": {},
  "meta": {
    "mnemo": "TestLis.PrihodnyeKassovyeOrdera",
    "title": {
      "ru_RU": "Приходные кассовые ордера",
      "en_EN": "Prihodnye kassovye ordera"
    },
    "description": {}
  }
}