{
  "publiccatalog": false,
  "levelscount": 2,
  "kodlength": 11,
  "titlelength": 150,
  "autonumerizer": true,
  "uniquecontrol": true,
  "kodseries": "CatalogScope",
  "kodtype": "Text",
  "mainview": "KodTitle",
  "oneformforelementandgroup": false,
  "editing": "Both",
  "requisites": [
    {
      "periodical": true,
      "sort": false,
      "selectbyrequisite": false,
      "usefor": "ForElement",
      "canbechangedbydocuments": false,
      "meta": {
        "mnemo": "tap.ObektyFinansovyhVlozheniii.Kontragentemitent",
        "title": {
          "ru_RU": "Контрагент (эмитент)",
          "en_EN": "Kontragent emitent"
        },
        "description": {}
      },
      "type": {
        "mnemo": "tap.Kontragenty"
      },
      "properties": {},
      "required": true
    },
    {
      "periodical": true,
      "sort": false,
      "selectbyrequisite": false,
      "usefor": "ForElement",
      "canbechangedbydocuments": false,
      "meta": {
        "mnemo": "tap.ObektyFinansovyhVlozheniii.VidVlozheniya",
        "title": {
          "ru_RU": "Вид вложения",
          "en_EN": "Vid vlozheniya"
        },
        "description": {}
      },
      "type": {
        "mnemo": "tap.VidyFinansovyhVlozheniii"
      },
      "properties": {},
      "required": true
    },
    {
      "periodical": true,
      "sort": false,
      "selectbyrequisite": false,
      "usefor": "ForElement",
      "canbechangedbydocuments": false,
      "meta": {
        "mnemo": "tap.ObektyFinansovyhVlozheniii.FormaUchastiyaVKapitale",
        "title": {
          "ru_RU": "Форма участия в капитале",
          "en_EN": "Forma uchastiya v kapitale"
        },
        "description": {}
      },
      "type": {
        "mnemo": "tap.FormyUchastiyaVKapitale"
      },
      "properties": {},
      "required": false
    },
    {
      "periodical": true,
      "sort": false,
      "selectbyrequisite": false,
      "usefor": "ForElement",
      "canbechangedbydocuments": false,
      "meta": {
        "mnemo": "tap.ObektyFinansovyhVlozheniii.DolyaVProcentah",
        "title": {
          "ru_RU": "Доля в процентах",
          "en_EN": "Dolya v procentah"
        },
        "description": {
          "ru_RU": "Доля (вклад) в уставном (складочном) капитале (процентов)"
        }
      },
      "type": {
        "mnemo": "primitive.real"
      },
      "properties": {
        "precision": "4",
        "length": "1",
        "unsigned": "false"
      },
      "required": false
    },
    {
      "periodical": false,
      "sort": false,
      "selectbyrequisite": false,
      "usefor": "ForElement",
      "meta": {
        "mnemo": "tap.ObektyFinansovyhVlozheniii.DataVypiskiIzReestraAkcionerov",
        "title": {
          "ru_RU": "Дата выписки из реестра акционеров",
          "en_EN": "Data vypiski iz reestra akcionerov"
        },
        "description": {}
      },
      "type": {
        "mnemo": "primitive.date"
      },
      "properties": {},
      "required": false
    },
    {
      "periodical": false,
      "sort": false,
      "selectbyrequisite": false,
      "usefor": "ForElement",
      "meta": {
        "mnemo": "tap.ObektyFinansovyhVlozheniii.NominalnyiiDerzhatel",
        "title": {
          "ru_RU": "Номинальный держатель",
          "en_EN": "Nominalnyii derzhatel"
        },
        "description": {}
      },
      "type": {
        "mnemo": "tap.Kontragenty"
      },
      "properties": {},
      "required": false
    }
  ],
  "form": {
    "script": {
      "title": "script",
      "sources": ""
    }
  },
  "formelement": {
    "title": "formElement",
    "script": {
      "title": "script",
      "sources": ""
    }
  },
  "formgroup": {
    "script": {
      "title": "script",
      "sources": ""
    }
  },
  "listformset": [],
  "script": {
    "title": "script",
    "sources": ""
  },
  "grants": {},
  "meta": {
    "mnemo": "tap.ObektyFinansovyhVlozheniii",
    "title": {
      "ru_RU": "Объекты финансовых вложений"
    },
    "description": {
      "ru_RU": "Справочник Объекты финансовых вложений"
    }
  }
}