{
  "active": true,
  "code": "02451",
  "name": {
    "ru_RU": "ОС - недвижимое имущество казны, переданное в доверительное управление"
  },
  "foreign": false,
  "numerical": true,
  "amounttype": "None",
  "offbalance": true,
  "type": "Active",
  "analyticsList": [
    {
      "type": {
        "mnemo": "tap.Kontragenty"
      },
      "returnsOnly": false,
      "bySum": false,
      "byForeignSum": false,
      "byNum": false,
      "analyticNumber": 0
    },
    {
      "type": {
        "mnemo": "tap.OsnovnyeSredstva"
      },
      "returnsOnly": false,
      "bySum": false,
      "byForeignSum": false,
      "byNum": false,
      "analyticNumber": 1
    }
  ],
  "propertyValues": {},
  "grants": {},
  "meta": {
    "mnemo": "02451",
    "title": {
      "ru_RU": "02451"
    },
    "description": {}
  }
}