{
  "active": true,
  "code": "2421",
  "name": {
    "ru_RU": "Основные средства – особо ценное движимое имущество в доверительном управлении"
  },
  "foreign": false,
  "numerical": true,
  "amounttype": "None",
  "journalnumber": "",
  "kosgudb": "",
  "kosgukr": "",
  "budgetclassificationtype": "None",
  "offbalance": true,
  "type": "Active",
  "analyticsList": [
    {
      "type": {
        "mnemo": "tap.Kontragenty"
      },
      "returnsOnly": false,
      "bySum": false,
      "byForeignSum": false,
      "byNum": false,
      "analyticNumber": 0
    },
    {
      "type": {
        "mnemo": "tap.OsnovnyeSredstva"
      },
      "returnsOnly": false,
      "bySum": false,
      "byForeignSum": false,
      "byNum": false,
      "analyticNumber": 1
    }
  ],
  "propertyValues": {},
  "grants": {},
  "meta": {
    "mnemo": "2421",
    "title": {
      "ru_RU": "2421"
    },
    "description": {}
  }
}