{
  "active": true,
  "code": "20520",
  "name": {
    "ru_RU": "Расчеты по доходам от собственности"
  },
  "foreign": false,
  "numerical": false,
  "amounttype": "None",
  "budgetclassificationtype": "None",
  "offbalance": false,
  "type": "ActivePassive",
  "analyticsList": [
    {
      "type": {
        "mnemo": "tap.Kontragenty"
      },
      "returnsOnly": false,
      "bySum": false,
      "byForeignSum": false,
      "byNum": false,
      "analyticNumber": 0
    }
  ],
  "propertyValues": {},
  "grants": {},
  "meta": {
    "mnemo": "20520",
    "title": {
      "ru_RU": "20520"
    },
    "description": {}
  }
}